{
   "dspt" : {
      "max" : "1.1.1.1.3"
   },
   "matches" : {
      "tags" : {
         "count" : 799
      },
      "preserve" : {
         "count" : 61
      },
      "url" : {
         "count" : 896
      },
      "series" : {
         "count" : 37
      },
      "description" : {
         "count" : 266
      },
      "libName" : {
         "count" : 0
      },
      "title" : {
         "count" : 799
      },
      "author" : {
         "count" : 236
      },
      "section" : {
         "count" : 3
      },
      "NULL" : {
         "count" : 0
      }
   }
}
